cmm_measurement_parser.py
cmm_measurement_parser-1.1.0.dist-info/licenses/LICENSE
cmm_measurement_parser-1.1.0.dist-info/METADATA
cmm_measurement_parser-1.1.0.dist-info/WHEEL
cmm_measurement_parser-1.1.0.dist-info/top_level.txt
cmm_measurement_parser-1.1.0.dist-info/RECORD
